LICENSE
README.rst
pyproject.toml
setup.cfg
setup.py
taskcontext/__init__.py
taskcontext/core.py
taskcontext/example.py
taskcontext/example_parallel.py
taskcontext.egg-info/PKG-INFO
taskcontext.egg-info/SOURCES.txt
taskcontext.egg-info/dependency_links.txt
taskcontext.egg-info/not-zip-safe
taskcontext.egg-info/requires.txt
taskcontext.egg-info/top_level.txt