Metadata-Version: 2.1
Name: taskcontext
Version: 0.1.0
Summary: TaskManager with context resolution
Home-page: https://github.com/mortbauer/taskcontext
Author: Martin Ortbauer
Author-email: mortbauer@gmail.com
License: MIT
Platform: UNKNOWN
Classifier: Intended Audience :: End Users/Desktop
Classifier: License :: OSI Approved :: MIT License
Classifier: Operating System :: OS Independent
Classifier: Programming Language :: Python :: 3
Classifier: Programming Language :: Python :: 3.7
Classifier: Programming Language :: Python :: 3.8
Requires-Python: >= 3.7
Provides-Extra: test
Provides-Extra: lint
Provides-Extra: dev
Provides-Extra: release
